setup.py
imeffect/__init__.py
imeffect/_util.pyx
imeffect/base.py
imeffect/basic.py
imeffect/blender.py
imeffect/layer.py
imeffect/pool.py
imeffect/preset.py
imeffect.egg-info/PKG-INFO
imeffect.egg-info/SOURCES.txt
imeffect.egg-info/dependency_links.txt
imeffect.egg-info/not-zip-safe
imeffect.egg-info/requires.txt
imeffect.egg-info/top_level.txt