Metadata-Version: 1.1
Name: imeffect
Version: 0.1.0
Summary: Image filter implementations written in Python (with scikit-image).
Home-page: http://jason2506.github.io/imeffect/
Author: Chi-En Wu
Author-email: UNKNOWN
License: The BSD 3-Clause License
Platform: any
Classifier: Intended Audience :: Developers
Classifier: License :: OSI Approved :: BSD License
Classifier: Operating System :: OS Independent
Classifier: Programming Language :: Python
Classifier: Programming Language :: Python :: 2.7
Classifier: Topic :: Software Development :: Libraries :: Python Modules
